{
  "$schema": "https://json-schema.org/draft/2020-12/schema",
  "title": "Domain Rules Schema",
  "type": "object",
  "required": ["version", "rules"],
  "properties": {
    "version": {"type": "integer", "minimum": 1},
    "rules": {
      "type": "array",
      "items": {
        "type": "object",
        "required": ["id", "domain", "mode"],
        "properties": {
          "id": {"type": "string", "minLength": 1},
          "domain": {"type": "string", "minLength": 1},
          "mode": {"type": "string", "enum": ["score", "default"]},
          "signals": {"type": "object"},
          "threshold": {"type": "number"},
          "weights": {"type": "object"}
        },
        "additionalProperties": true
      }
    }
  },
  "additionalProperties": true
}
